datasets/__init__.py
datasets/iris.py
datasets/metadata.py
datasets/mnist_digits.py
datasets/spiral.py
datasets/utils.py
merlin/__init__.py
merlin/deprecated_hpqnn_model.py
merlin/mlp_model.py
merlin/pqnn_model.py
pcvl_pytorch/__init__.py
pcvl_pytorch/pcvl2torch.py
pcvl_pytorch/pcvl2torchscript.py
pcvl_pytorch/sanity-test.py
pcvl_pytorch/slos_torch.py
pcvl_pytorch/slos_torchscript.py
merlin_quandela_preview-0.1.0.dist-info/METADATA
merlin_quandela_preview-0.1.0.dist-info/WHEEL
merlin_quandela_preview-0.1.0.dist-info/top_level.txt
merlin_quandela_preview-0.1.0.dist-info/RECORD
